{
  "kind": "collectionType",
  "collectionName": "tracer-studies",
  "info": {
    "name": "Tracer Study",
    "description": ""
  },
  "options": {
    "increments": true,
    "timestamps": true,
    "draftAndPublish": false
  },
  "pluginOptions": {},
  "attributes": {
    "graduation_description": {
      "type": "richtext",
      "required": true
    },
    "graphs": {
      "collection": "file",
      "via": "related",
      "allowedTypes": [
        "images"
      ],
      "plugin": "upload",
      "required": true,
      "pluginOptions": {}
    },
    "job_description": {
      "type": "richtext",
      "required": true
    },
    "title": {
      "type": "string"
    }
  }
}
